[{"senderKeyId":153198052,"senderChainKey":{"iteration":10,"seed":"TyH2LD+3z5di2kaybvF/hV+bH22v68R7y0KYtFY7uqQ="},"senderSigningKey":{"public":"BXRPM9yJ4IzuRLZrmGIE8nBlPPbXx3mfUqASVexGy7JT"},"senderMessageKeys":[]},{"senderKeyId":1831773494,"senderChainKey":{"iteration":400,"seed":"89WRX5M9lJ+TP0u+d2LDRCwZqpgO+e5WODddUSd1Bec="},"senderSigningKey":{"public":"BUW73Upct1nypYjjddPUTshCtmM4TnhILp2PwGbi2Es5"},"senderMessageKeys":[{},{},{},{},{},{},{},{},{},{},{},{},{},{},{},{},{},{},{},{},{},{},{},{},{},{},{},{},{},{},{},{},{},{},{},{},{},{},{},{},{},{},{},{},{},{},{},{},{},{},{},{},{},{},{},{},{},{},{},{},{},{},{},{},{},{},{},{},{},{},{},{},{},{},{},{},{},{},{},{},{},{},{},{},{},{},{},{},{},{},{},{},{},{},{},{},{},{},{},{},{},{},{},{},{},{},{},{},{},{},{},{},{},{},{},{},{},{},{},{},{},{},{},{},{},{},{},{},{},{},{},{},{},{},{},{},{},{},{},{},{},{},{},{},{},{},{},{},{},{},{},{},{},{},{},{},{},{},{},{},{},{},{},{},{},{},{},{}]}]