[{"senderKeyId":1316889092,"senderChainKey":{"iteration":101,"seed":"DIonAKqWzMG7NTETiYIk7fFnPylZ9GffQZZTKnUTzAw="},"senderSigningKey":{"public":"BS/dfDBUpcXCe7Qiok9PG4VtvR96xEzj8I8wsCs7z8wj"},"senderMessageKeys":[{},{},{},{},{},{},{},{},{},{},{},{},{},{},{},{},{},{},{},{},{},{},{},{},{},{},{},{},{},{},{},{}]},{"senderKeyId":1316889092,"senderChainKey":{"iteration":48,"seed":"lCx49e1ljdYFjLqBafIE3P6jG2Qkn8cPGa9rZHGbIlw="},"senderSigningKey":{"public":"BS/dfDBUpcXCe7Qiok9PG4VtvR96xEzj8I8wsCs7z8wj"},"senderMessageKeys":[]},{"senderKeyId":146818195,"senderChainKey":{"iteration":263,"seed":"CaJ5S18Os6g7UHwYWzVxf0t+oFw3IYFqvEKAVbeZObg="},"senderSigningKey":{"public":"BRW0IKjTgvQhHLb6676893fQtSZNs1oBtKDlkNJT4eht"},"senderMessageKeys":[{},{},{},{},{},{},{},{},{},{},{},{},{},{},{},{},{},{},{},{},{},{},{},{},{},{},{},{},{},{},{},{},{},{},{},{},{},{},{},{},{},{},{},{},{},{},{},{},{},{},{},{},{},{},{},{},{},{},{},{},{},{},{},{},{},{},{},{},{},{},{},{},{},{},{},{},{},{},{},{},{},{},{},{},{},{},{},{},{},{},{},{},{},{},{},{},{},{},{},{},{},{},{},{},{},{},{},{},{},{},{},{},{},{},{},{},{},{},{},{},{},{},{},{},{},{},{},{},{},{},{},{}]},{"senderKeyId":1613926247,"senderChainKey":{"iteration":6,"seed":"LketDwmSBjIX0EqHD2y8Ac1t8v8AaIz0FD/QdbNm+F0="},"senderSigningKey":{"public":"BQo0n9q9Qwbqmqcd6ot9QNEVX4WpDQ6Md8dhI4DPBnp1"},"senderMessageKeys":[]},{"senderKeyId":1613926247,"senderChainKey":{"iteration":5,"seed":"RtYZfw/aHMtqFVf/9s0I2IhL4WMTC05O97taShfictM="},"senderSigningKey":{"public":"BQo0n9q9Qwbqmqcd6ot9QNEVX4WpDQ6Md8dhI4DPBnp1"},"senderMessageKeys":[]}]